json_sempai-0.4.0.dist-info/DESCRIPTION.rst
json_sempai-0.4.0.dist-info/top_level.txt
json_sempai-0.4.0.dist-info/RECORD
json_sempai-0.4.0.dist-info/METADATA
json_sempai-0.4.0.dist-info/WHEEL
json_sempai-0.4.0.dist-info/metadata.json
jsonsempai/sempai.py
jsonsempai/__init__.py
jsonsempai/magic.py
jsonsempai/tests/test_sempai.py
jsonsempai/tests/__init__.py
