Metadata-Version: 2.0
Name: json-sempai
Version: 0.4.0
Summary: Use JSON files as if they're python modules
Home-page: https://github.com/kragniz/json-sempai
Author: Louis Taylor
Author-email: kragniz@gmail.com
License: MIT
Keywords: please don't use this library for anything
Platform: UNKNOWN
Classifier: Intended Audience :: Developers
Classifier: License :: OSI Approved :: MIT License
Classifier: Programming Language :: Python
Classifier: Programming Language :: Python :: 2.6
Classifier: Programming Language :: Python :: 2.7
Classifier: Programming Language :: Python :: 3.2
Classifier: Programming Language :: Python :: 3.3
Classifier: Programming Language :: Python :: 3.4
